[
    {
        "exchangeSegment": 2,
        "exchangeInstrumentID": 38805
    },
    {
        "exchangeSegment": 2,
        "exchangeInstrumentID": 39902
    },
    {
        "exchangeSegment": 2,
        "exchangeInstrumentID": 9973982
    },
    {
        "exchangeSegment": 2,
        "exchangeInstrumentID": 38946
    },
    {
        "exchangeSegment": 2,
        "exchangeInstrumentID": 40397
    },
    {
        "exchangeSegment": 2,
        "exchangeInstrumentID": 10010573
    },
    {
        "exchangeSegment": 2,
        "exchangeInstrumentID": 39363
    },
    {
        "exchangeSegment": 2,
        "exchangeInstrumentID": 73345
    },
    {
        "exchangeSegment": 2,
        "exchangeInstrumentID": 10150273
    },
    {
        "exchangeSegment": 2,
        "exchangeInstrumentID": 35033
    },
    {
        "exchangeSegment": 2,
        "exchangeInstrumentID": 35057
    },
    {
        "exchangeSegment": 2,
        "exchangeInstrumentID": 9003505
    },
    {
        "exchangeSegment": 2,
        "exchangeInstrumentID": 35401
    },
    {
        "exchangeSegment": 2,
        "exchangeInstrumentID": 73259
    },
    {
        "exchangeSegment": 2,
        "exchangeInstrumentID": 9135915
    },
    {
        "exchangeSegment": 2,
        "exchangeInstrumentID": 43343
    },
    {
        "exchangeSegment": 2,
        "exchangeInstrumentID": 73537
    },
    {
        "exchangeSegment": 2,
        "exchangeInstrumentID": 11169345
    },
    {
        "exchangeSegment": 2,
        "exchangeInstrumentID": 39173
    },
    {
        "exchangeSegment": 2,
        "exchangeInstrumentID": 42277
    },
    {
        "exchangeSegment": 2,
        "exchangeInstrumentID": 10070565
    },
    {
        "exchangeSegment": 2,
        "exchangeInstrumentID": 35569
    },
    {
        "exchangeSegment": 2,
        "exchangeInstrumentID": 35403
    },
    {
        "exchangeSegment": 2,
        "exchangeInstrumentID": 9141067
    },
    {
        "exchangeSegment": 2,
        "exchangeInstrumentID": 38736
    },
    {
        "exchangeSegment": 2,
        "exchangeInstrumentID": 9955779
    },
    {
        "exchangeSegment": 2,
        "exchangeInstrumentID": 35823
    },
    {
        "exchangeSegment": 2,
        "exchangeInstrumentID": 35406
    },
    {
        "exchangeSegment": 2,
        "exchangeInstrumentID": 9206094
    },
    {
        "exchangeSegment": 2,
        "exchangeInstrumentID": 39209
    },
    {
        "exchangeSegment": 2,
        "exchangeInstrumentID": 43177
    },
    {
        "exchangeSegment": 2,
        "exchangeInstrumentID": 10080681
    },
    {
        "exchangeSegment": 2,
        "exchangeInstrumentID": 35213
    },
    {
        "exchangeSegment": 2,
        "exchangeInstrumentID": 69078
    },
    {
        "exchangeSegment": 2,
        "exchangeInstrumentID": 9083606
    },
    {
        "exchangeSegment": 2,
        "exchangeInstrumentID": 38881
    },
    {
        "exchangeSegment": 2,
        "exchangeInstrumentID": 39930
    },
    {
        "exchangeSegment": 2,
        "exchangeInstrumentID": 9993466
    },
    {
        "exchangeSegment": 2,
        "exchangeInstrumentID": 43450
    },
    {
        "exchangeSegment": 2,
        "exchangeInstrumentID": 73692
    },
    {
        "exchangeSegment": 2,
        "exchangeInstrumentID": 11196892
    },
    {
        "exchangeSegment": 2,
        "exchangeInstrumentID": 41130
    },
    {
        "exchangeSegment": 2,
        "exchangeInstrumentID": 43329
    },
    {
        "exchangeSegment": 2,
        "exchangeInstrumentID": 10572609
    },
    {
        "exchangeSegment": 2,
        "exchangeInstrumentID": 35968
    },
    {
        "exchangeSegment": 2,
        "exchangeInstrumentID": 73306
    },
    {
        "exchangeSegment": 2,
        "exchangeInstrumentID": 9281114
    },
    {
        "exchangeSegment": 2,
        "exchangeInstrumentID": 43160
    },
    {
        "exchangeSegment": 2,
        "exchangeInstrumentID": 73490
    },
    {
        "exchangeSegment": 2,
        "exchangeInstrumentID": 11122450
    },
    {
        "exchangeSegment": 2,
        "exchangeInstrumentID": 35203
    },
    {
        "exchangeSegment": 2,
        "exchangeInstrumentID": 65554
    },
    {
        "exchangeSegment": 2,
        "exchangeInstrumentID": 9077522
    },
    {
        "exchangeSegment": 2,
        "exchangeInstrumentID": 35032
    },
    {
        "exchangeSegment": 2,
        "exchangeInstrumentID": 35053
    },
    {
        "exchangeSegment": 2,
        "exchangeInstrumentID": 9003245
    },
    {
        "exchangeSegment": 2,
        "exchangeInstrumentID": 39910
    },
    {
        "exchangeSegment": 2,
        "exchangeInstrumentID": 73386
    },
    {
        "exchangeSegment": 2,
        "exchangeInstrumentID": 10290346
    },
    {
        "exchangeSegment": 2,
        "exchangeInstrumentID": 43344
    },
    {
        "exchangeSegment": 2,
        "exchangeInstrumentID": 73561
    },
    {
        "exchangeSegment": 2,
        "exchangeInstrumentID": 11169625
    },
    {
        "exchangeSegment": 2,
        "exchangeInstrumentID": 41407
    },
    {
        "exchangeSegment": 2,
        "exchangeInstrumentID": 43378
    },
    {
        "exchangeSegment": 2,
        "exchangeInstrumentID": 10643570
    },
    {
        "exchangeSegment": 2,
        "exchangeInstrumentID": 35393
    },
    {
        "exchangeSegment": 2,
        "exchangeInstrumentID": 35345
    },
    {
        "exchangeSegment": 2,
        "exchangeInstrumentID": 9095953
    },
    {
        "exchangeSegment": 2,
        "exchangeInstrumentID": 40380
    },
    {
        "exchangeSegment": 2,
        "exchangeInstrumentID": 43250
    },
    {
        "exchangeSegment": 2,
        "exchangeInstrumentID": 10380530
    },
    {
        "exchangeSegment": 2,
        "exchangeInstrumentID": 41029
    },
    {
        "exchangeSegment": 2,
        "exchangeInstrumentID": 73464
    },
    {
        "exchangeSegment": 2,
        "exchangeInstrumentID": 10576888
    },
    {
        "exchangeSegment": 2,
        "exchangeInstrumentID": 43407
    },
    {
        "exchangeSegment": 2,
        "exchangeInstrumentID": 73672
    },
    {
        "exchangeSegment": 2,
        "exchangeInstrumentID": 11185864
    },
    {
        "exchangeSegment": 2,
        "exchangeInstrumentID": 41384
    },
    {
        "exchangeSegment": 2,
        "exchangeInstrumentID": 43371
    },
    {
        "exchangeSegment": 2,
        "exchangeInstrumentID": 10637675
    },
    {
        "exchangeSegment": 2,
        "exchangeInstrumentID": 41301
    },
    {
        "exchangeSegment": 2,
        "exchangeInstrumentID": 43349
    },
    {
        "exchangeSegment": 2,
        "exchangeInstrumentID": 10616405
    },
    {
        "exchangeSegment": 2,
        "exchangeInstrumentID": 43369
    },
    {
        "exchangeSegment": 2,
        "exchangeInstrumentID": 73574
    },
    {
        "exchangeSegment": 2,
        "exchangeInstrumentID": 11176038
    },
    {
        "exchangeSegment": 2,
        "exchangeInstrumentID": 35195
    },
    {
        "exchangeSegment": 2,
        "exchangeInstrumentID": 65552
    },
    {
        "exchangeSegment": 2,
        "exchangeInstrumentID": 9075472
    },
    {
        "exchangeSegment": 2,
        "exchangeInstrumentID": 41302
    },
    {
        "exchangeSegment": 2,
        "exchangeInstrumentID": 43351
    },
    {
        "exchangeSegment": 2,
        "exchangeInstrumentID": 10616663
    },
    {
        "exchangeSegment": 2,
        "exchangeInstrumentID": 35358
    },
    {
        "exchangeSegment": 2,
        "exchangeInstrumentID": 69095
    },
    {
        "exchangeSegment": 2,
        "exchangeInstrumentID": 9120743
    },
    {
        "exchangeSegment": 2,
        "exchangeInstrumentID": 41033
    },
    {
        "exchangeSegment": 2,
        "exchangeInstrumentID": 73465
    },
    {
        "exchangeSegment": 2,
        "exchangeInstrumentID": 10577913
    },
    {
        "exchangeSegment": 2,
        "exchangeInstrumentID": 39192
    },
    {
        "exchangeSegment": 2,
        "exchangeInstrumentID": 43153
    },
    {
        "exchangeSegment": 2,
        "exchangeInstrumentID": 10076305
    },
    {
        "exchangeSegment": 2,
        "exchangeInstrumentID": 38947
    },
    {
        "exchangeSegment": 2,
        "exchangeInstrumentID": 40399
    },
    {
        "exchangeSegment": 2,
        "exchangeInstrumentID": 10010831
    },
    {
        "exchangeSegment": 2,
        "exchangeInstrumentID": 73432
    },
    {
        "exchangeSegment": 2,
        "exchangeInstrumentID": 10415576
    },
    {
        "exchangeSegment": 2,
        "exchangeInstrumentID": 43328
    },
    {
        "exchangeSegment": 2,
        "exchangeInstrumentID": 73530
    },
    {
        "exchangeSegment": 2,
        "exchangeInstrumentID": 11165498
    },
    {
        "exchangeSegment": 2,
        "exchangeInstrumentID": 38529
    },
    {
        "exchangeSegment": 2,
        "exchangeInstrumentID": 37309
    },
    {
        "exchangeSegment": 2,
        "exchangeInstrumentID": 9900733
    },
    {
        "exchangeSegment": 2,
        "exchangeInstrumentID": 38822
    },
    {
        "exchangeSegment": 2,
        "exchangeInstrumentID": 9978342
    },
    {
        "exchangeSegment": 2,
        "exchangeInstrumentID": 35736
    },
    {
        "exchangeSegment": 2,
        "exchangeInstrumentID": 35405
    },
    {
        "exchangeSegment": 2,
        "exchangeInstrumentID": 9183821
    },
    {
        "exchangeSegment": 2,
        "exchangeInstrumentID": 40478
    },
    {
        "exchangeSegment": 2,
        "exchangeInstrumentID": 73436
    },
    {
        "exchangeSegment": 2,
        "exchangeInstrumentID": 10435804
    },
    {
        "exchangeSegment": 2,
        "exchangeInstrumentID": 43387
    },
    {
        "exchangeSegment": 2,
        "exchangeInstrumentID": 73579
    },
    {
        "exchangeSegment": 2,
        "exchangeInstrumentID": 11180651
    },
    {
        "exchangeSegment": 2,
        "exchangeInstrumentID": 38525
    },
    {
        "exchangeSegment": 2,
        "exchangeInstrumentID": 36389
    },
    {
        "exchangeSegment": 2,
        "exchangeInstrumentID": 9898789
    },
    {
        "exchangeSegment": 2,
        "exchangeInstrumentID": 35565
    },
    {
        "exchangeSegment": 2,
        "exchangeInstrumentID": 73280
    },
    {
        "exchangeSegment": 2,
        "exchangeInstrumentID": 9177920
    },
    {
        "exchangeSegment": 2,
        "exchangeInstrumentID": 38098
    },
    {
        "exchangeSegment": 2,
        "exchangeInstrumentID": 35564
    },
    {
        "exchangeSegment": 2,
        "exchangeInstrumentID": 9788652
    },
    {
        "exchangeSegment": 2,
        "exchangeInstrumentID": 38916
    },
    {
        "exchangeSegment": 2,
        "exchangeInstrumentID": 40386
    },
    {
        "exchangeSegment": 2,
        "exchangeInstrumentID": 10002882
    },
    {
        "exchangeSegment": 2,
        "exchangeInstrumentID": 39696
    },
    {
        "exchangeSegment": 2,
        "exchangeInstrumentID": 43227
    },
    {
        "exchangeSegment": 2,
        "exchangeInstrumentID": 10205403
    },
    {
        "exchangeSegment": 2,
        "exchangeInstrumentID": 35451
    },
    {
        "exchangeSegment": 2,
        "exchangeInstrumentID": 9110814
    },
    {
        "exchangeSegment": 2,
        "exchangeInstrumentID": 35017
    },
    {
        "exchangeSegment": 2,
        "exchangeInstrumentID": 35008
    },
    {
        "exchangeSegment": 2,
        "exchangeInstrumentID": 8999360
    },
    {
        "exchangeSegment": 2,
        "exchangeInstrumentID": 39194
    },
    {
        "exchangeSegment": 2,
        "exchangeInstrumentID": 43157
    },
    {
        "exchangeSegment": 2,
        "exchangeInstrumentID": 10076821
    },
    {
        "exchangeSegment": 2,
        "exchangeInstrumentID": 73488
    },
    {
        "exchangeSegment": 2,
        "exchangeInstrumentID": 11121680
    },
    {
        "exchangeSegment": 2,
        "exchangeInstrumentID": 73266
    },
    {
        "exchangeSegment": 2,
        "exchangeInstrumentID": 9136946
    },
    {
        "exchangeSegment": 2,
        "exchangeInstrumentID": 40368
    },
    {
        "exchangeSegment": 2,
        "exchangeInstrumentID": 43229
    },
    {
        "exchangeSegment": 2,
        "exchangeInstrumentID": 10377437
    },
    {
        "exchangeSegment": 2,
        "exchangeInstrumentID": 39203
    },
    {
        "exchangeSegment": 2,
        "exchangeInstrumentID": 43174
    },
    {
        "exchangeSegment": 2,
        "exchangeInstrumentID": 10079142
    },
    {
        "exchangeSegment": 2,
        "exchangeInstrumentID": 43428
    },
    {
        "exchangeSegment": 2,
        "exchangeInstrumentID": 73679
    },
    {
        "exchangeSegment": 2,
        "exchangeInstrumentID": 11191247
    },
    {
        "exchangeSegment": 2,
        "exchangeInstrumentID": 43339
    },
    {
        "exchangeSegment": 2,
        "exchangeInstrumentID": 73535
    },
    {
        "exchangeSegment": 2,
        "exchangeInstrumentID": 11168319
    },
    {
        "exchangeSegment": 2,
        "exchangeInstrumentID": 35428
    },
    {
        "exchangeSegment": 2,
        "exchangeInstrumentID": 73272
    },
    {
        "exchangeSegment": 2,
        "exchangeInstrumentID": 9142840
    },
    {
        "exchangeSegment": 2,
        "exchangeInstrumentID": 40480
    },
    {
        "exchangeSegment": 2,
        "exchangeInstrumentID": 43268
    },
    {
        "exchangeSegment": 2,
        "exchangeInstrumentID": 10406148
    },
    {
        "exchangeSegment": 2,
        "exchangeInstrumentID": 38429
    },
    {
        "exchangeSegment": 2,
        "exchangeInstrumentID": 35801
    },
    {
        "exchangeSegment": 2,
        "exchangeInstrumentID": 9873625
    },
    {
        "exchangeSegment": 2,
        "exchangeInstrumentID": 38108
    },
    {
        "exchangeSegment": 2,
        "exchangeInstrumentID": 35570
    },
    {
        "exchangeSegment": 2,
        "exchangeInstrumentID": 9791218
    },
    {
        "exchangeSegment": 2,
        "exchangeInstrumentID": 73522
    },
    {
        "exchangeSegment": 2,
        "exchangeInstrumentID": 73523
    },
    {
        "exchangeSegment": 2,
        "exchangeInstrumentID": 18895155
    },
    {
        "exchangeSegment": 2,
        "exchangeInstrumentID": 43355
    },
    {
        "exchangeSegment": 2,
        "exchangeInstrumentID": 73564
    },
    {
        "exchangeSegment": 2,
        "exchangeInstrumentID": 11172444
    },
    {
        "exchangeSegment": 2,
        "exchangeInstrumentID": 40927
    },
    {
        "exchangeSegment": 2,
        "exchangeInstrumentID": 43312
    },
    {
        "exchangeSegment": 2,
        "exchangeInstrumentID": 10520624
    },
    {
        "exchangeSegment": 2,
        "exchangeInstrumentID": 35350
    },
    {
        "exchangeSegment": 2,
        "exchangeInstrumentID": 69091
    },
    {
        "exchangeSegment": 2,
        "exchangeInstrumentID": 9118691
    },
    {
        "exchangeSegment": 2,
        "exchangeInstrumentID": 43278
    },
    {
        "exchangeSegment": 2,
        "exchangeInstrumentID": 73519
    },
    {
        "exchangeSegment": 2,
        "exchangeInstrumentID": 11152687
    },
    {
        "exchangeSegment": 2,
        "exchangeInstrumentID": 39199
    },
    {
        "exchangeSegment": 2,
        "exchangeInstrumentID": 43173
    },
    {
        "exchangeSegment": 2,
        "exchangeInstrumentID": 10078117
    },
    {
        "exchangeSegment": 2,
        "exchangeInstrumentID": 35432
    },
    {
        "exchangeSegment": 2,
        "exchangeInstrumentID": 73273
    },
    {
        "exchangeSegment": 2,
        "exchangeInstrumentID": 9143865
    },
    {
        "exchangeSegment": 2,
        "exchangeInstrumentID": 35176
    },
    {
        "exchangeSegment": 2,
        "exchangeInstrumentID": 35223
    },
    {
        "exchangeSegment": 2,
        "exchangeInstrumentID": 9040279
    },
    {
        "exchangeSegment": 2,
        "exchangeInstrumentID": 40369
    },
    {
        "exchangeSegment": 2,
        "exchangeInstrumentID": 43230
    },
    {
        "exchangeSegment": 2,
        "exchangeInstrumentID": 10377694
    },
    {
        "exchangeSegment": 2,
        "exchangeInstrumentID": 43104
    },
    {
        "exchangeSegment": 2,
        "exchangeInstrumentID": 73479
    },
    {
        "exchangeSegment": 2,
        "exchangeInstrumentID": 11108103
    },
    {
        "exchangeSegment": 2,
        "exchangeInstrumentID": 38503
    },
    {
        "exchangeSegment": 2,
        "exchangeInstrumentID": 36227
    },
    {
        "exchangeSegment": 2,
        "exchangeInstrumentID": 9892995
    },
    {
        "exchangeSegment": 2,
        "exchangeInstrumentID": 43195
    },
    {
        "exchangeSegment": 2,
        "exchangeInstrumentID": 73497
    },
    {
        "exchangeSegment": 2,
        "exchangeInstrumentID": 11131417
    },
    {
        "exchangeSegment": 2,
        "exchangeInstrumentID": 43298
    },
    {
        "exchangeSegment": 2,
        "exchangeInstrumentID": 73524
    },
    {
        "exchangeSegment": 2,
        "exchangeInstrumentID": 11157812
    },
    {
        "exchangeSegment": 2,
        "exchangeInstrumentID": 43405
    },
    {
        "exchangeSegment": 2,
        "exchangeInstrumentID": 73670
    },
    {
        "exchangeSegment": 2,
        "exchangeInstrumentID": 11185350
    },
    {
        "exchangeSegment": 2,
        "exchangeInstrumentID": 73475
    },
    {
        "exchangeSegment": 2,
        "exchangeInstrumentID": 10896387
    },
    {
        "exchangeSegment": 2,
        "exchangeInstrumentID": 73287
    },
    {
        "exchangeSegment": 2,
        "exchangeInstrumentID": 9238343
    },
    {
        "exchangeSegment": 2,
        "exchangeInstrumentID": 39217
    },
    {
        "exchangeSegment": 2,
        "exchangeInstrumentID": 43196
    },
    {
        "exchangeSegment": 2,
        "exchangeInstrumentID": 10082748
    },
    {
        "exchangeSegment": 2,
        "exchangeInstrumentID": 41303
    },
    {
        "exchangeSegment": 2,
        "exchangeInstrumentID": 10616923
    },
    {
        "exchangeSegment": 2,
        "exchangeInstrumentID": 38747
    },
    {
        "exchangeSegment": 2,
        "exchangeInstrumentID": 39368
    },
    {
        "exchangeSegment": 2,
        "exchangeInstrumentID": 9958600
    },
    {
        "exchangeSegment": 2,
        "exchangeInstrumentID": 43370
    },
    {
        "exchangeSegment": 2,
        "exchangeInstrumentID": 73575
    },
    {
        "exchangeSegment": 2,
        "exchangeInstrumentID": 11176295
    },
    {
        "exchangeSegment": 2,
        "exchangeInstrumentID": 38453
    },
    {
        "exchangeSegment": 2,
        "exchangeInstrumentID": 35816
    },
    {
        "exchangeSegment": 2,
        "exchangeInstrumentID": 9879784
    },
    {
        "exchangeSegment": 2,
        "exchangeInstrumentID": 43377
    },
    {
        "exchangeSegment": 2,
        "exchangeInstrumentID": 73577
    },
    {
        "exchangeSegment": 2,
        "exchangeInstrumentID": 11178089
    },
    {
        "exchangeSegment": 2,
        "exchangeInstrumentID": 41451
    },
    {
        "exchangeSegment": 2,
        "exchangeInstrumentID": 43390
    },
    {
        "exchangeSegment": 2,
        "exchangeInstrumentID": 10654846
    },
    {
        "exchangeSegment": 2,
        "exchangeInstrumentID": 37337
    },
    {
        "exchangeSegment": 2,
        "exchangeInstrumentID": 73326
    },
    {
        "exchangeSegment": 2,
        "exchangeInstrumentID": 9631598
    },
    {
        "exchangeSegment": 2,
        "exchangeInstrumentID": 39107
    },
    {
        "exchangeSegment": 2,
        "exchangeInstrumentID": 41577
    },
    {
        "exchangeSegment": 2,
        "exchangeInstrumentID": 10052969
    },
    {
        "exchangeSegment": 2,
        "exchangeInstrumentID": 43451
    },
    {
        "exchangeSegment": 2,
        "exchangeInstrumentID": 73693
    },
    {
        "exchangeSegment": 2,
        "exchangeInstrumentID": 11197149
    },
    {
        "exchangeSegment": 2,
        "exchangeInstrumentID": 41505
    },
    {
        "exchangeSegment": 2,
        "exchangeInstrumentID": 43401
    },
    {
        "exchangeSegment": 2,
        "exchangeInstrumentID": 10668681
    },
    {
        "exchangeSegment": 2,
        "exchangeInstrumentID": 40978
    },
    {
        "exchangeSegment": 2,
        "exchangeInstrumentID": 43327
    },
    {
        "exchangeSegment": 2,
        "exchangeInstrumentID": 10533695
    },
    {
        "exchangeSegment": 2,
        "exchangeInstrumentID": 35117
    },
    {
        "exchangeSegment": 2,
        "exchangeInstrumentID": 54445
    },
    {
        "exchangeSegment": 2,
        "exchangeInstrumentID": 9044397
    },
    {
        "exchangeSegment": 2,
        "exchangeInstrumentID": 41498
    },
    {
        "exchangeSegment": 2,
        "exchangeInstrumentID": 43400
    },
    {
        "exchangeSegment": 2,
        "exchangeInstrumentID": 10666888
    },
    {
        "exchangeSegment": 2,
        "exchangeInstrumentID": 35080
    },
    {
        "exchangeSegment": 2,
        "exchangeInstrumentID": 35187
    },
    {
        "exchangeSegment": 2,
        "exchangeInstrumentID": 9015667
    },
    {
        "exchangeSegment": 2,
        "exchangeInstrumentID": 40381
    },
    {
        "exchangeSegment": 2,
        "exchangeInstrumentID": 43251
    },
    {
        "exchangeSegment": 2,
        "exchangeInstrumentID": 10380787
    },
    {
        "exchangeSegment": 2,
        "exchangeInstrumentID": 38263
    },
    {
        "exchangeSegment": 2,
        "exchangeInstrumentID": 35769
    },
    {
        "exchangeSegment": 2,
        "exchangeInstrumentID": 9831097
    },
    {
        "exchangeSegment": 2,
        "exchangeInstrumentID": 39052
    },
    {
        "exchangeSegment": 2,
        "exchangeInstrumentID": 73331
    },
    {
        "exchangeSegment": 2,
        "exchangeInstrumentID": 10070643
    },
    {
        "exchangeSegment": 2,
        "exchangeInstrumentID": 35274
    },
    {
        "exchangeSegment": 2,
        "exchangeInstrumentID": 69086
    },
    {
        "exchangeSegment": 2,
        "exchangeInstrumentID": 9099230
    },
    {
        "exchangeSegment": 2,
        "exchangeInstrumentID": 35245
    },
    {
        "exchangeSegment": 2,
        "exchangeInstrumentID": 69084
    },
    {
        "exchangeSegment": 2,
        "exchangeInstrumentID": 9091804
    },
    {
        "exchangeSegment": 2,
        "exchangeInstrumentID": 35019
    },
    {
        "exchangeSegment": 2,
        "exchangeInstrumentID": 35052
    },
    {
        "exchangeSegment": 2,
        "exchangeInstrumentID": 8999916
    },
    {
        "exchangeSegment": 2,
        "exchangeInstrumentID": 35329
    },
    {
        "exchangeSegment": 2,
        "exchangeInstrumentID": 35275
    },
    {
        "exchangeSegment": 2,
        "exchangeInstrumentID": 9079499
    },
    {
        "exchangeSegment": 2,
        "exchangeInstrumentID": 39219
    },
    {
        "exchangeSegment": 2,
        "exchangeInstrumentID": 43200
    },
    {
        "exchangeSegment": 2,
        "exchangeInstrumentID": 10083264
    },
    {
        "exchangeSegment": 2,
        "exchangeInstrumentID": 40412
    },
    {
        "exchangeSegment": 2,
        "exchangeInstrumentID": 73434
    },
    {
        "exchangeSegment": 2,
        "exchangeInstrumentID": 10418906
    },
    {
        "exchangeSegment": 2,
        "exchangeInstrumentID": 43156
    },
    {
        "exchangeSegment": 2,
        "exchangeInstrumentID": 73487
    },
    {
        "exchangeSegment": 2,
        "exchangeInstrumentID": 11121423
    },
    {
        "exchangeSegment": 2,
        "exchangeInstrumentID": 9020341
    },
    {
        "exchangeSegment": 2,
        "exchangeInstrumentID": 73279
    },
    {
        "exchangeSegment": 2,
        "exchangeInstrumentID": 9177663
    },
    {
        "exchangeSegment": 2,
        "exchangeInstrumentID": 43252
    },
    {
        "exchangeSegment": 2,
        "exchangeInstrumentID": 73512
    },
    {
        "exchangeSegment": 2,
        "exchangeInstrumentID": 11146024
    },
    {
        "exchangeSegment": 2,
        "exchangeInstrumentID": 35152
    },
    {
        "exchangeSegment": 2,
        "exchangeInstrumentID": 9034125
    },
    {
        "exchangeSegment": 2,
        "exchangeInstrumentID": 73529
    },
    {
        "exchangeSegment": 2,
        "exchangeInstrumentID": 11165241
    },
    {
        "exchangeSegment": 2,
        "exchangeInstrumentID": 39345
    },
    {
        "exchangeSegment": 2,
        "exchangeInstrumentID": 73339
    },
    {
        "exchangeSegment": 2,
        "exchangeInstrumentID": 10145659
    },
    {
        "exchangeSegment": 2,
        "exchangeInstrumentID": 41310
    },
    {
        "exchangeSegment": 2,
        "exchangeInstrumentID": 43357
    },
    {
        "exchangeSegment": 2,
        "exchangeInstrumentID": 10618717
    },
    {
        "exchangeSegment": 2,
        "exchangeInstrumentID": 35453
    },
    {
        "exchangeSegment": 2,
        "exchangeInstrumentID": 35359
    },
    {
        "exchangeSegment": 2,
        "exchangeInstrumentID": 9111327
    },
    {
        "exchangeSegment": 2,
        "exchangeInstrumentID": 35362
    },
    {
        "exchangeSegment": 2,
        "exchangeInstrumentID": 73149
    },
    {
        "exchangeSegment": 2,
        "exchangeInstrumentID": 9125821
    },
    {
        "exchangeSegment": 2,
        "exchangeInstrumentID": 73467
    },
    {
        "exchangeSegment": 2,
        "exchangeInstrumentID": 10717179
    },
    {
        "exchangeSegment": 2,
        "exchangeInstrumentID": 35004
    },
    {
        "exchangeSegment": 2,
        "exchangeInstrumentID": 54446
    },
    {
        "exchangeSegment": 2,
        "exchangeInstrumentID": 9015470
    },
    {
        "exchangeSegment": 2,
        "exchangeInstrumentID": 41288
    },
    {
        "exchangeSegment": 2,
        "exchangeInstrumentID": 43342
    },
    {
        "exchangeSegment": 2,
        "exchangeInstrumentID": 10613070
    },
    {
        "exchangeSegment": 2,
        "exchangeInstrumentID": 37233
    },
    {
        "exchangeSegment": 2,
        "exchangeInstrumentID": 35427
    },
    {
        "exchangeSegment": 2,
        "exchangeInstrumentID": 9567075
    },
    {
        "exchangeSegment": 2,
        "exchangeInstrumentID": 39198
    },
    {
        "exchangeSegment": 2,
        "exchangeInstrumentID": 10077848
    },
    {
        "exchangeSegment": 2,
        "exchangeInstrumentID": 43120
    },
    {
        "exchangeSegment": 2,
        "exchangeInstrumentID": 73483
    },
    {
        "exchangeSegment": 2,
        "exchangeInstrumentID": 11112203
    },
    {
        "exchangeSegment": 2,
        "exchangeInstrumentID": 35410
    },
    {
        "exchangeSegment": 2,
        "exchangeInstrumentID": 73268
    },
    {
        "exchangeSegment": 2,
        "exchangeInstrumentID": 9138228
    },
    {
        "exchangeSegment": 2,
        "exchangeInstrumentID": 73510
    },
    {
        "exchangeSegment": 2,
        "exchangeInstrumentID": 11145510
    },
    {
        "exchangeSegment": 2,
        "exchangeInstrumentID": 69096
    },
    {
        "exchangeSegment": 2,
        "exchangeInstrumentID": 9121000
    },
    {
        "exchangeSegment": 2,
        "exchangeInstrumentID": 43119
    },
    {
        "exchangeSegment": 2,
        "exchangeInstrumentID": 73482
    },
    {
        "exchangeSegment": 2,
        "exchangeInstrumentID": 11111946
    },
    {
        "exchangeSegment": 2,
        "exchangeInstrumentID": 38885
    },
    {
        "exchangeSegment": 2,
        "exchangeInstrumentID": 40384
    },
    {
        "exchangeSegment": 2,
        "exchangeInstrumentID": 9994944
    },
    {
        "exchangeSegment": 2,
        "exchangeInstrumentID": 39189
    },
    {
        "exchangeSegment": 2,
        "exchangeInstrumentID": 43121
    },
    {
        "exchangeSegment": 2,
        "exchangeInstrumentID": 10075505
    },
    {
        "exchangeSegment": 2,
        "exchangeInstrumentID": 37512
    },
    {
        "exchangeSegment": 2,
        "exchangeInstrumentID": 35533
    },
    {
        "exchangeSegment": 2,
        "exchangeInstrumentID": 9638605
    },
    {
        "exchangeSegment": 2,
        "exchangeInstrumentID": 35708
    },
    {
        "exchangeSegment": 2,
        "exchangeInstrumentID": 35404
    },
    {
        "exchangeSegment": 2,
        "exchangeInstrumentID": 9176652
    },
    {
        "exchangeSegment": 2,
        "exchangeInstrumentID": 35524
    },
    {
        "exchangeSegment": 2,
        "exchangeInstrumentID": 73274
    },
    {
        "exchangeSegment": 2,
        "exchangeInstrumentID": 9167418
    },
    {
        "exchangeSegment": 2,
        "exchangeInstrumentID": 35247
    },
    {
        "exchangeSegment": 2,
        "exchangeInstrumentID": 69085
    },
    {
        "exchangeSegment": 2,
        "exchangeInstrumentID": 9092317
    },
    {
        "exchangeSegment": 2,
        "exchangeInstrumentID": 73566
    },
    {
        "exchangeSegment": 2,
        "exchangeInstrumentID": 11172958
    },
    {
        "exchangeSegment": 2,
        "exchangeInstrumentID": 41513
    },
    {
        "exchangeSegment": 2,
        "exchangeInstrumentID": 43406
    },
    {
        "exchangeSegment": 2,
        "exchangeInstrumentID": 10670734
    },
    {
        "exchangeSegment": 2,
        "exchangeInstrumentID": 73576
    },
    {
        "exchangeSegment": 2,
        "exchangeInstrumentID": 11176552
    },
    {
        "exchangeSegment": 2,
        "exchangeInstrumentID": 43389
    },
    {
        "exchangeSegment": 2,
        "exchangeInstrumentID": 73620
    },
    {
        "exchangeSegment": 2,
        "exchangeInstrumentID": 11181204
    },
    {
        "exchangeSegment": 2,
        "exchangeInstrumentID": 41547
    },
    {
        "exchangeSegment": 2,
        "exchangeInstrumentID": 43427
    },
    {
        "exchangeSegment": 2,
        "exchangeInstrumentID": 10679459
    },
    {
        "exchangeSegment": 2,
        "exchangeInstrumentID": 35232
    },
    {
        "exchangeSegment": 2,
        "exchangeInstrumentID": 69083
    },
    {
        "exchangeSegment": 2,
        "exchangeInstrumentID": 9088475
    },
    {
        "exchangeSegment": 2,
        "exchangeInstrumentID": 43266
    },
    {
        "exchangeSegment": 2,
        "exchangeInstrumentID": 73514
    },
    {
        "exchangeSegment": 2,
        "exchangeInstrumentID": 11149610
    },
    {
        "exchangeSegment": 2,
        "exchangeInstrumentID": 35454
    },
    {
        "exchangeSegment": 2,
        "exchangeInstrumentID": 35361
    },
    {
        "exchangeSegment": 2,
        "exchangeInstrumentID": 9111585
    },
    {
        "exchangeSegment": 2,
        "exchangeInstrumentID": 38573
    },
    {
        "exchangeSegment": 2,
        "exchangeInstrumentID": 9913740
    },
    {
        "exchangeSegment": 2,
        "exchangeInstrumentID": 38476
    },
    {
        "exchangeSegment": 2,
        "exchangeInstrumentID": 35861
    },
    {
        "exchangeSegment": 2,
        "exchangeInstrumentID": 9885717
    },
    {
        "exchangeSegment": 2,
        "exchangeInstrumentID": 9000893
    },
    {
        "exchangeSegment": 2,
        "exchangeInstrumentID": 43438
    },
    {
        "exchangeSegment": 2,
        "exchangeInstrumentID": 73687
    },
    {
        "exchangeSegment": 2,
        "exchangeInstrumentID": 11193815
    },
    {
        "exchangeSegment": 2,
        "exchangeInstrumentID": 39122
    },
    {
        "exchangeSegment": 2,
        "exchangeInstrumentID": 41615
    },
    {
        "exchangeSegment": 2,
        "exchangeInstrumentID": 10056847
    },
    {
        "exchangeSegment": 2,
        "exchangeInstrumentID": 39040
    },
    {
        "exchangeSegment": 2,
        "exchangeInstrumentID": 10035273
    },
    {
        "exchangeSegment": 2,
        "exchangeInstrumentID": 38571
    },
    {
        "exchangeSegment": 2,
        "exchangeInstrumentID": 37352
    },
    {
        "exchangeSegment": 2,
        "exchangeInstrumentID": 9911528
    },
    {
        "exchangeSegment": 2,
        "exchangeInstrumentID": 35025
    },
    {
        "exchangeSegment": 2,
        "exchangeInstrumentID": 54457
    },
    {
        "exchangeSegment": 2,
        "exchangeInstrumentID": 9020857
    },
    {
        "exchangeSegment": 2,
        "exchangeInstrumentID": 39362
    },
    {
        "exchangeSegment": 2,
        "exchangeInstrumentID": 73344
    },
    {
        "exchangeSegment": 2,
        "exchangeInstrumentID": 10150016
    },
    {
        "exchangeSegment": 2,
        "exchangeInstrumentID": 54832
    },
    {
        "exchangeSegment": 2,
        "exchangeInstrumentID": 9028400
    },
    {
        "exchangeSegment": 2,
        "exchangeInstrumentID": 41441
    },
    {
        "exchangeSegment": 2,
        "exchangeInstrumentID": 43388
    },
    {
        "exchangeSegment": 2,
        "exchangeInstrumentID": 10652284
    },
    {
        "exchangeSegment": 2,
        "exchangeInstrumentID": 35296
    },
    {
        "exchangeSegment": 2,
        "exchangeInstrumentID": 9071008
    },
    {
        "exchangeSegment": 2,
        "exchangeInstrumentID": 73570
    },
    {
        "exchangeSegment": 2,
        "exchangeInstrumentID": 73571
    },
    {
        "exchangeSegment": 2,
        "exchangeInstrumentID": 18907491
    },
    {
        "exchangeSegment": 2,
        "exchangeInstrumentID": 35144
    },
    {
        "exchangeSegment": 2,
        "exchangeInstrumentID": 9032067
    },
    {
        "exchangeSegment": 2,
        "exchangeInstrumentID": 73562
    },
    {
        "exchangeSegment": 2,
        "exchangeInstrumentID": 11170906
    },
    {
        "exchangeSegment": 2,
        "exchangeInstrumentID": 9015733
    },
    {
        "exchangeSegment": 2,
        "exchangeInstrumentID": 35335
    },
    {
        "exchangeSegment": 2,
        "exchangeInstrumentID": 35333
    },
    {
        "exchangeSegment": 2,
        "exchangeInstrumentID": 9081093
    },
    {
        "exchangeSegment": 2,
        "exchangeInstrumentID": 43267
    },
    {
        "exchangeSegment": 2,
        "exchangeInstrumentID": 73515
    },
    {
        "exchangeSegment": 2,
        "exchangeInstrumentID": 11149867
    },
    {
        "exchangeSegment": 2,
        "exchangeInstrumentID": 39181
    },
    {
        "exchangeSegment": 2,
        "exchangeInstrumentID": 43113
    },
    {
        "exchangeSegment": 2,
        "exchangeInstrumentID": 10073449
    },
    {
        "exchangeSegment": 2,
        "exchangeInstrumentID": 35143
    },
    {
        "exchangeSegment": 2,
        "exchangeInstrumentID": 35201
    },
    {
        "exchangeSegment": 2,
        "exchangeInstrumentID": 9031809
    },
    {
        "exchangeSegment": 2,
        "exchangeInstrumentID": 43358
    },
    {
        "exchangeSegment": 2,
        "exchangeInstrumentID": 73567
    },
    {
        "exchangeSegment": 2,
        "exchangeInstrumentID": 11173215
    },
    {
        "exchangeSegment": 2,
        "exchangeInstrumentID": 37513
    },
    {
        "exchangeSegment": 2,
        "exchangeInstrumentID": 35560
    },
    {
        "exchangeSegment": 2,
        "exchangeInstrumentID": 9638888
    },
    {
        "exchangeSegment": 2,
        "exchangeInstrumentID": 38676
    },
    {
        "exchangeSegment": 2,
        "exchangeInstrumentID": 39353
    },
    {
        "exchangeSegment": 2,
        "exchangeInstrumentID": 9940409
    },
    {
        "exchangeSegment": 2,
        "exchangeInstrumentID": 35423
    },
    {
        "exchangeSegment": 2,
        "exchangeInstrumentID": 35351
    },
    {
        "exchangeSegment": 2,
        "exchangeInstrumentID": 9103639
    },
    {
        "exchangeSegment": 2,
        "exchangeInstrumentID": 43417
    },
    {
        "exchangeSegment": 2,
        "exchangeInstrumentID": 73674
    },
    {
        "exchangeSegment": 2,
        "exchangeInstrumentID": 11188426
    },
    {
        "exchangeSegment": 2,
        "exchangeInstrumentID": 39111
    },
    {
        "exchangeSegment": 2,
        "exchangeInstrumentID": 41610
    },
    {
        "exchangeSegment": 2,
        "exchangeInstrumentID": 10054026
    },
    {
        "exchangeSegment": 2,
        "exchangeInstrumentID": 58958
    },
    {
        "exchangeSegment": 2,
        "exchangeInstrumentID": 15147693
    },
    {
        "exchangeSegment": 2,
        "exchangeInstrumentID": 38877
    },
    {
        "exchangeSegment": 2,
        "exchangeInstrumentID": 39929
    },
    {
        "exchangeSegment": 2,
        "exchangeInstrumentID": 9992441
    },
    {
        "exchangeSegment": 2,
        "exchangeInstrumentID": 54458
    },
    {
        "exchangeSegment": 2,
        "exchangeInstrumentID": 9027770
    },
    {
        "exchangeSegment": 2,
        "exchangeInstrumentID": 35793
    },
    {
        "exchangeSegment": 2,
        "exchangeInstrumentID": 73284
    },
    {
        "exchangeSegment": 2,
        "exchangeInstrumentID": 9236292
    },
    {
        "exchangeSegment": 2,
        "exchangeInstrumentID": 73578
    },
    {
        "exchangeSegment": 2,
        "exchangeInstrumentID": 11178346
    },
    {
        "exchangeSegment": 2,
        "exchangeInstrumentID": 40861
    },
    {
        "exchangeSegment": 2,
        "exchangeInstrumentID": 43277
    },
    {
        "exchangeSegment": 2,
        "exchangeInstrumentID": 10503693
    },
    {
        "exchangeSegment": 2,
        "exchangeInstrumentID": 41321
    },
    {
        "exchangeSegment": 2,
        "exchangeInstrumentID": 43365
    },
    {
        "exchangeSegment": 2,
        "exchangeInstrumentID": 10621541
    },
    {
        "exchangeSegment": 2,
        "exchangeInstrumentID": 73527
    },
    {
        "exchangeSegment": 2,
        "exchangeInstrumentID": 11161399
    },
    {
        "exchangeSegment": 2,
        "exchangeInstrumentID": 35411
    },
    {
        "exchangeSegment": 2,
        "exchangeInstrumentID": 73270
    },
    {
        "exchangeSegment": 2,
        "exchangeInstrumentID": 9138486
    },
    {
        "exchangeSegment": 2,
        "exchangeInstrumentID": 35455
    },
    {
        "exchangeSegment": 2,
        "exchangeInstrumentID": 9111842
    },
    {
        "exchangeSegment": 2,
        "exchangeInstrumentID": 41452
    },
    {
        "exchangeSegment": 2,
        "exchangeInstrumentID": 43391
    },
    {
        "exchangeSegment": 2,
        "exchangeInstrumentID": 10655103
    },
    {
        "exchangeSegment": 2,
        "exchangeInstrumentID": 38111
    },
    {
        "exchangeSegment": 2,
        "exchangeInstrumentID": 35571
    },
    {
        "exchangeSegment": 2,
        "exchangeInstrumentID": 9791987
    },
    {
        "exchangeSegment": 2,
        "exchangeInstrumentID": 38725
    },
    {
        "exchangeSegment": 2,
        "exchangeInstrumentID": 39357
    },
    {
        "exchangeSegment": 2,
        "exchangeInstrumentID": 9952957
    },
    {
        "exchangeSegment": 2,
        "exchangeInstrumentID": 43269
    },
    {
        "exchangeSegment": 2,
        "exchangeInstrumentID": 73517
    },
    {
        "exchangeSegment": 2,
        "exchangeInstrumentID": 11150381
    },
    {
        "exchangeSegment": 2,
        "exchangeInstrumentID": 41385
    },
    {
        "exchangeSegment": 2,
        "exchangeInstrumentID": 10637937
    },
    {
        "exchangeSegment": 2,
        "exchangeInstrumentID": 73303
    },
    {
        "exchangeSegment": 2,
        "exchangeInstrumentID": 9242199
    },
    {
        "exchangeSegment": 2,
        "exchangeInstrumentID": 73484
    },
    {
        "exchangeSegment": 2,
        "exchangeInstrumentID": 11112460
    },
    {
        "exchangeSegment": 2,
        "exchangeInstrumentID": 40881
    },
    {
        "exchangeSegment": 2,
        "exchangeInstrumentID": 43310
    },
    {
        "exchangeSegment": 2,
        "exchangeInstrumentID": 10508846
    },
    {
        "exchangeSegment": 2,
        "exchangeInstrumentID": 69090
    },
    {
        "exchangeSegment": 2,
        "exchangeInstrumentID": 9117410
    },
    {
        "exchangeSegment": 2,
        "exchangeInstrumentID": 69097
    },
    {
        "exchangeSegment": 2,
        "exchangeInstrumentID": 9121513
    },
    {
        "exchangeSegment": 2,
        "exchangeInstrumentID": 41511
    },
    {
        "exchangeSegment": 2,
        "exchangeInstrumentID": 10670221
    },
    {
        "exchangeSegment": 2,
        "exchangeInstrumentID": 43199
    },
    {
        "exchangeSegment": 2,
        "exchangeInstrumentID": 73499
    },
    {
        "exchangeSegment": 2,
        "exchangeInstrumentID": 11132443
    },
    {
        "exchangeSegment": 2,
        "exchangeInstrumentID": 37492
    },
    {
        "exchangeSegment": 2,
        "exchangeInstrumentID": 9633384
    },
    {
        "exchangeSegment": 2,
        "exchangeInstrumentID": 36165
    },
    {
        "exchangeSegment": 2,
        "exchangeInstrumentID": 9293651
    },
    {
        "exchangeSegment": 2,
        "exchangeInstrumentID": 35216
    },
    {
        "exchangeSegment": 2,
        "exchangeInstrumentID": 69080
    },
    {
        "exchangeSegment": 2,
        "exchangeInstrumentID": 9084376
    },
    {
        "exchangeSegment": 2,
        "exchangeInstrumentID": 41311
    },
    {
        "exchangeSegment": 2,
        "exchangeInstrumentID": 10618974
    },
    {
        "exchangeSegment": 2,
        "exchangeInstrumentID": 43292
    },
    {
        "exchangeSegment": 2,
        "exchangeInstrumentID": 35000
    },
    {
        "exchangeSegment": 2,
        "exchangeInstrumentID": 11117752
    },
    {
        "exchangeSegment": 2,
        "exchangeInstrumentID": 35311
    },
    {
        "exchangeSegment": 2,
        "exchangeInstrumentID": 9074863
    },
    {
        "exchangeSegment": 2,
        "exchangeInstrumentID": 38597
    },
    {
        "exchangeSegment": 2,
        "exchangeInstrumentID": 9920177
    },
    {
        "exchangeSegment": 2,
        "exchangeInstrumentID": 41603
    },
    {
        "exchangeSegment": 2,
        "exchangeInstrumentID": 10693819
    },
    {
        "exchangeSegment": 2,
        "exchangeInstrumentID": 38999
    },
    {
        "exchangeSegment": 2,
        "exchangeInstrumentID": 40481
    },
    {
        "exchangeSegment": 2,
        "exchangeInstrumentID": 10024225
    },
    {
        "exchangeSegment": 2,
        "exchangeInstrumentID": 40930
    },
    {
        "exchangeSegment": 2,
        "exchangeInstrumentID": 43313
    },
    {
        "exchangeSegment": 2,
        "exchangeInstrumentID": 10521393
    },
    {
        "exchangeSegment": 2,
        "exchangeInstrumentID": 40979
    },
    {
        "exchangeSegment": 2,
        "exchangeInstrumentID": 10533952
    },
    {
        "exchangeSegment": 2,
        "exchangeInstrumentID": 40473
    },
    {
        "exchangeSegment": 2,
        "exchangeInstrumentID": 43253
    },
    {
        "exchangeSegment": 2,
        "exchangeInstrumentID": 10404341
    },
    {
        "exchangeSegment": 2,
        "exchangeInstrumentID": 73580
    },
    {
        "exchangeSegment": 2,
        "exchangeInstrumentID": 11180908
    },
    {
        "exchangeSegment": 2,
        "exchangeInstrumentID": 35013
    },
    {
        "exchangeSegment": 2,
        "exchangeInstrumentID": 54452
    },
    {
        "exchangeSegment": 2,
        "exchangeInstrumentID": 9017780
    },
    {
        "exchangeSegment": 2,
        "exchangeInstrumentID": 35421
    },
    {
        "exchangeSegment": 2,
        "exchangeInstrumentID": 9103126
    },
    {
        "exchangeSegment": 2,
        "exchangeInstrumentID": 35188
    },
    {
        "exchangeSegment": 2,
        "exchangeInstrumentID": 57247
    },
    {
        "exchangeSegment": 2,
        "exchangeInstrumentID": 9065375
    },
    {
        "exchangeSegment": 2,
        "exchangeInstrumentID": 73267
    },
    {
        "exchangeSegment": 2,
        "exchangeInstrumentID": 9137203
    },
    {
        "exchangeSegment": 2,
        "exchangeInstrumentID": 54833
    },
    {
        "exchangeSegment": 2,
        "exchangeInstrumentID": 9029425
    },
    {
        "exchangeSegment": 2,
        "exchangeInstrumentID": 35076
    },
    {
        "exchangeSegment": 2,
        "exchangeInstrumentID": 35185
    },
    {
        "exchangeSegment": 2,
        "exchangeInstrumentID": 9014641
    },
    {
        "exchangeSegment": 2,
        "exchangeInstrumentID": 73626
    },
    {
        "exchangeSegment": 2,
        "exchangeInstrumentID": 11181722
    },
    {
        "exchangeSegment": 2,
        "exchangeInstrumentID": 73513
    },
    {
        "exchangeSegment": 2,
        "exchangeInstrumentID": 11146281
    },
    {
        "exchangeSegment": 2,
        "exchangeInstrumentID": 41284
    },
    {
        "exchangeSegment": 2,
        "exchangeInstrumentID": 43330
    },
    {
        "exchangeSegment": 2,
        "exchangeInstrumentID": 10612034
    },
    {
        "exchangeSegment": 2,
        "exchangeInstrumentID": 43114
    },
    {
        "exchangeSegment": 2,
        "exchangeInstrumentID": 73481
    },
    {
        "exchangeSegment": 2,
        "exchangeInstrumentID": 11110665
    },
    {
        "exchangeSegment": 2,
        "exchangeInstrumentID": 38495
    },
    {
        "exchangeSegment": 2,
        "exchangeInstrumentID": 9890688
    },
    {
        "exchangeSegment": 2,
        "exchangeInstrumentID": 39354
    },
    {
        "exchangeSegment": 2,
        "exchangeInstrumentID": 73342
    },
    {
        "exchangeSegment": 2,
        "exchangeInstrumentID": 10147966
    },
    {
        "exchangeSegment": 2,
        "exchangeInstrumentID": 39184
    },
    {
        "exchangeSegment": 2,
        "exchangeInstrumentID": 10074218
    },
    {
        "exchangeSegment": 2,
        "exchangeInstrumentID": 35018
    },
    {
        "exchangeSegment": 2,
        "exchangeInstrumentID": 8999633
    },
    {
        "exchangeSegment": 2,
        "exchangeInstrumentID": 38724
    },
    {
        "exchangeSegment": 2,
        "exchangeInstrumentID": 9952698
    },
    {
        "exchangeSegment": 2,
        "exchangeInstrumentID": 35456
    },
    {
        "exchangeSegment": 2,
        "exchangeInstrumentID": 35400
    },
    {
        "exchangeSegment": 2,
        "exchangeInstrumentID": 9112136
    },
    {
        "exchangeSegment": 2,
        "exchangeInstrumentID": 73367
    },
    {
        "exchangeSegment": 2,
        "exchangeInstrumentID": 10288279
    },
    {
        "exchangeSegment": 2,
        "exchangeInstrumentID": 73281
    },
    {
        "exchangeSegment": 2,
        "exchangeInstrumentID": 9179201
    },
    {
        "exchangeSegment": 2,
        "exchangeInstrumentID": 35839
    },
    {
        "exchangeSegment": 2,
        "exchangeInstrumentID": 9210194
    },
    {
        "exchangeSegment": 2,
        "exchangeInstrumentID": 41289
    },
    {
        "exchangeSegment": 2,
        "exchangeInstrumentID": 10613327
    },
    {
        "exchangeSegment": 2,
        "exchangeInstrumentID": 39220
    },
    {
        "exchangeSegment": 2,
        "exchangeInstrumentID": 43211
    },
    {
        "exchangeSegment": 2,
        "exchangeInstrumentID": 10083531
    },
    {
        "exchangeSegment": 2,
        "exchangeInstrumentID": 35001
    },
    {
        "exchangeSegment": 2,
        "exchangeInstrumentID": 9014708
    },
    {
        "exchangeSegment": 2,
        "exchangeInstrumentID": 39188
    },
    {
        "exchangeSegment": 2,
        "exchangeInstrumentID": 10075248
    },
    {
        "exchangeSegment": 2,
        "exchangeInstrumentID": 37310
    },
    {
        "exchangeSegment": 2,
        "exchangeInstrumentID": 73325
    },
    {
        "exchangeSegment": 2,
        "exchangeInstrumentID": 9624685
    },
    {
        "exchangeSegment": 2,
        "exchangeInstrumentID": 41463
    },
    {
        "exchangeSegment": 2,
        "exchangeInstrumentID": 43396
    },
    {
        "exchangeSegment": 2,
        "exchangeInstrumentID": 10657924
    },
    {
        "exchangeSegment": 2,
        "exchangeInstrumentID": 73341
    },
    {
        "exchangeSegment": 2,
        "exchangeInstrumentID": 10147709
    },
    {
        "exchangeSegment": 2,
        "exchangeInstrumentID": 73275
    },
    {
        "exchangeSegment": 2,
        "exchangeInstrumentID": 9169723
    },
    {
        "exchangeSegment": 2,
        "exchangeInstrumentID": 73528
    },
    {
        "exchangeSegment": 2,
        "exchangeInstrumentID": 11161656
    },
    {
        "exchangeSegment": 2,
        "exchangeInstrumentID": 73628
    },
    {
        "exchangeSegment": 2,
        "exchangeInstrumentID": 11183004
    },
    {
        "exchangeSegment": 2,
        "exchangeInstrumentID": 41523
    },
    {
        "exchangeSegment": 2,
        "exchangeInstrumentID": 10673295
    },
    {
        "exchangeSegment": 2,
        "exchangeInstrumentID": 73625
    },
    {
        "exchangeSegment": 2,
        "exchangeInstrumentID": 11181465
    },
    {
        "exchangeSegment": 2,
        "exchangeInstrumentID": 41620
    },
    {
        "exchangeSegment": 2,
        "exchangeInstrumentID": 73474
    },
    {
        "exchangeSegment": 2,
        "exchangeInstrumentID": 10728194
    },
    {
        "exchangeSegment": 2,
        "exchangeInstrumentID": 43297
    },
    {
        "exchangeSegment": 2,
        "exchangeInstrumentID": 73520
    },
    {
        "exchangeSegment": 2,
        "exchangeInstrumentID": 11157552
    },
    {
        "exchangeSegment": 2,
        "exchangeInstrumentID": 41366
    },
    {
        "exchangeSegment": 2,
        "exchangeInstrumentID": 10633066
    },
    {
        "exchangeSegment": 2,
        "exchangeInstrumentID": 73563
    },
    {
        "exchangeSegment": 2,
        "exchangeInstrumentID": 11171419
    },
    {
        "exchangeSegment": 2,
        "exchangeInstrumentID": 73271
    },
    {
        "exchangeSegment": 2,
        "exchangeInstrumentID": 9142583
    },
    {
        "exchangeSegment": 2,
        "exchangeInstrumentID": 73324
    },
    {
        "exchangeSegment": 2,
        "exchangeInstrumentID": 9624428
    },
    {
        "exchangeSegment": 2,
        "exchangeInstrumentID": 41604
    },
    {
        "exchangeSegment": 2,
        "exchangeInstrumentID": 43462
    },
    {
        "exchangeSegment": 2,
        "exchangeInstrumentID": 10694086
    },
    {
        "exchangeSegment": 2,
        "exchangeInstrumentID": 35015
    },
    {
        "exchangeSegment": 2,
        "exchangeInstrumentID": 35003
    },
    {
        "exchangeSegment": 2,
        "exchangeInstrumentID": 8998843
    },
    {
        "exchangeSegment": 2,
        "exchangeInstrumentID": 35154
    },
    {
        "exchangeSegment": 2,
        "exchangeInstrumentID": 35215
    },
    {
        "exchangeSegment": 2,
        "exchangeInstrumentID": 9034639
    },
    {
        "exchangeSegment": 2,
        "exchangeInstrumentID": 40482
    },
    {
        "exchangeSegment": 2,
        "exchangeInstrumentID": 73460
    },
    {
        "exchangeSegment": 2,
        "exchangeInstrumentID": 10436852
    },
    {
        "exchangeSegment": 2,
        "exchangeInstrumentID": 8998329
    },
    {
        "exchangeSegment": 2,
        "exchangeInstrumentID": 73500
    },
    {
        "exchangeSegment": 2,
        "exchangeInstrumentID": 11132700
    },
    {
        "exchangeSegment": 2,
        "exchangeInstrumentID": 9048910
    },
    {
        "exchangeSegment": 2,
        "exchangeInstrumentID": 35357
    },
    {
        "exchangeSegment": 2,
        "exchangeInstrumentID": 69094
    },
    {
        "exchangeSegment": 2,
        "exchangeInstrumentID": 9120486
    },
    {
        "exchangeSegment": 2,
        "exchangeInstrumentID": 38508
    },
    {
        "exchangeSegment": 2,
        "exchangeInstrumentID": 36388
    },
    {
        "exchangeSegment": 2,
        "exchangeInstrumentID": 9894436
    },
    {
        "exchangeSegment": 2,
        "exchangeInstrumentID": 39170
    },
    {
        "exchangeSegment": 2,
        "exchangeInstrumentID": 10069140
    },
    {
        "exchangeSegment": 2,
        "exchangeInstrumentID": 38570
    },
    {
        "exchangeSegment": 2,
        "exchangeInstrumentID": 9911257
    },
    {
        "exchangeSegment": 2,
        "exchangeInstrumentID": 39215
    },
    {
        "exchangeSegment": 2,
        "exchangeInstrumentID": 43188
    },
    {
        "exchangeSegment": 2,
        "exchangeInstrumentID": 10082228
    },
    {
        "exchangeSegment": 2,
        "exchangeInstrumentID": 38930
    },
    {
        "exchangeSegment": 2,
        "exchangeInstrumentID": 40393
    },
    {
        "exchangeSegment": 2,
        "exchangeInstrumentID": 10006473
    },
    {
        "exchangeSegment": 2,
        "exchangeInstrumentID": 73262
    },
    {
        "exchangeSegment": 2,
        "exchangeInstrumentID": 9136430
    },
    {
        "exchangeSegment": 2,
        "exchangeInstrumentID": 41462
    },
    {
        "exchangeSegment": 2,
        "exchangeInstrumentID": 43392
    },
    {
        "exchangeSegment": 2,
        "exchangeInstrumentID": 10657664
    },
    {
        "exchangeSegment": 2,
        "exchangeInstrumentID": 73518
    },
    {
        "exchangeSegment": 2,
        "exchangeInstrumentID": 11152430
    },
    {
        "exchangeSegment": 2,
        "exchangeInstrumentID": 37410
    },
    {
        "exchangeSegment": 2,
        "exchangeInstrumentID": 9612388
    },
    {
        "exchangeSegment": 2,
        "exchangeInstrumentID": 35310
    },
    {
        "exchangeSegment": 2,
        "exchangeInstrumentID": 9074605
    },
    {
        "exchangeSegment": 2,
        "exchangeInstrumentID": 40474
    },
    {
        "exchangeSegment": 2,
        "exchangeInstrumentID": 10404610
    },
    {
        "exchangeSegment": 2,
        "exchangeInstrumentID": 35087
    },
    {
        "exchangeSegment": 2,
        "exchangeInstrumentID": 9017460
    },
    {
        "exchangeSegment": 2,
        "exchangeInstrumentID": 43397
    },
    {
        "exchangeSegment": 2,
        "exchangeInstrumentID": 73629
    },
    {
        "exchangeSegment": 2,
        "exchangeInstrumentID": 11183261
    },
    {
        "exchangeSegment": 2,
        "exchangeInstrumentID": 39047
    },
    {
        "exchangeSegment": 2,
        "exchangeInstrumentID": 41576
    },
    {
        "exchangeSegment": 2,
        "exchangeInstrumentID": 10037608
    },
    {
        "exchangeSegment": 2,
        "exchangeInstrumentID": 35457
    },
    {
        "exchangeSegment": 2,
        "exchangeInstrumentID": 9112393
    },
    {
        "exchangeSegment": 2,
        "exchangeInstrumentID": 35120
    },
    {
        "exchangeSegment": 2,
        "exchangeInstrumentID": 9025915
    },
    {
        "exchangeSegment": 2,
        "exchangeInstrumentID": 35312
    },
    {
        "exchangeSegment": 2,
        "exchangeInstrumentID": 9075146
    },
    {
        "exchangeSegment": 2,
        "exchangeInstrumentID": 69087
    },
    {
        "exchangeSegment": 2,
        "exchangeInstrumentID": 9099487
    },
    {
        "exchangeSegment": 2,
        "exchangeInstrumentID": 39366
    },
    {
        "exchangeSegment": 2,
        "exchangeInstrumentID": 73348
    },
    {
        "exchangeSegment": 2,
        "exchangeInstrumentID": 10151044
    },
    {
        "exchangeSegment": 2,
        "exchangeInstrumentID": 73509
    },
    {
        "exchangeSegment": 2,
        "exchangeInstrumentID": 11140389
    },
    {
        "exchangeSegment": 2,
        "exchangeInstrumentID": 38526
    },
    {
        "exchangeSegment": 2,
        "exchangeInstrumentID": 36398
    },
    {
        "exchangeSegment": 2,
        "exchangeInstrumentID": 9899054
    },
    {
        "exchangeSegment": 2,
        "exchangeInstrumentID": 73671
    },
    {
        "exchangeSegment": 2,
        "exchangeInstrumentID": 11185607
    },
    {
        "exchangeSegment": 2,
        "exchangeInstrumentID": 73572
    },
    {
        "exchangeSegment": 2,
        "exchangeInstrumentID": 11175012
    },
    {
        "exchangeSegment": 2,
        "exchangeInstrumentID": 35356
    },
    {
        "exchangeSegment": 2,
        "exchangeInstrumentID": 69093
    },
    {
        "exchangeSegment": 2,
        "exchangeInstrumentID": 9120229
    },
    {
        "exchangeSegment": 2,
        "exchangeInstrumentID": 38292
    },
    {
        "exchangeSegment": 2,
        "exchangeInstrumentID": 35798
    },
    {
        "exchangeSegment": 2,
        "exchangeInstrumentID": 9838550
    },
    {
        "exchangeSegment": 2,
        "exchangeInstrumentID": 43360
    },
    {
        "exchangeSegment": 2,
        "exchangeInstrumentID": 73568
    },
    {
        "exchangeSegment": 2,
        "exchangeInstrumentID": 11173728
    },
    {
        "exchangeSegment": 2,
        "exchangeInstrumentID": 38099
    },
    {
        "exchangeSegment": 2,
        "exchangeInstrumentID": 9788909
    },
    {
        "exchangeSegment": 2,
        "exchangeInstrumentID": 41617
    },
    {
        "exchangeSegment": 2,
        "exchangeInstrumentID": 73473
    },
    {
        "exchangeSegment": 2,
        "exchangeInstrumentID": 10727425
    },
    {
        "exchangeSegment": 2,
        "exchangeInstrumentID": 73494
    },
    {
        "exchangeSegment": 2,
        "exchangeInstrumentID": 11126806
    },
    {
        "exchangeSegment": 2,
        "exchangeInstrumentID": 40875
    },
    {
        "exchangeSegment": 2,
        "exchangeInstrumentID": 10507297
    },
    {
        "exchangeSegment": 2,
        "exchangeInstrumentID": 39190
    },
    {
        "exchangeSegment": 2,
        "exchangeInstrumentID": 43122
    },
    {
        "exchangeSegment": 2,
        "exchangeInstrumentID": 10075762
    },
    {
        "exchangeSegment": 2,
        "exchangeInstrumentID": 54455
    },
    {
        "exchangeSegment": 2,
        "exchangeInstrumentID": 9015223
    },
    {
        "exchangeSegment": 2,
        "exchangeInstrumentID": 38815
    },
    {
        "exchangeSegment": 2,
        "exchangeInstrumentID": 39905
    },
    {
        "exchangeSegment": 2,
        "exchangeInstrumentID": 9976545
    },
    {
        "exchangeSegment": 2,
        "exchangeInstrumentID": 43212
    },
    {
        "exchangeSegment": 2,
        "exchangeInstrumentID": 73505
    },
    {
        "exchangeSegment": 2,
        "exchangeInstrumentID": 11135777
    },
    {
        "exchangeSegment": 2,
        "exchangeInstrumentID": 39699
    },
    {
        "exchangeSegment": 2,
        "exchangeInstrumentID": 43228
    },
    {
        "exchangeSegment": 2,
        "exchangeInstrumentID": 10206172
    },
    {
        "exchangeSegment": 2,
        "exchangeInstrumentID": 43437
    },
    {
        "exchangeSegment": 2,
        "exchangeInstrumentID": 73686
    },
    {
        "exchangeSegment": 2,
        "exchangeInstrumentID": 11193558
    },
    {
        "exchangeSegment": 2,
        "exchangeInstrumentID": 73305
    },
    {
        "exchangeSegment": 2,
        "exchangeInstrumentID": 9253721
    },
    {
        "exchangeSegment": 2,
        "exchangeInstrumentID": 39191
    },
    {
        "exchangeSegment": 2,
        "exchangeInstrumentID": 43152
    },
    {
        "exchangeSegment": 2,
        "exchangeInstrumentID": 10076048
    },
    {
        "exchangeSegment": 2,
        "exchangeInstrumentID": 39049
    },
    {
        "exchangeSegment": 2,
        "exchangeInstrumentID": 73330
    },
    {
        "exchangeSegment": 2,
        "exchangeInstrumentID": 10069874
    },
    {
        "exchangeSegment": 2,
        "exchangeInstrumentID": 73486
    },
    {
        "exchangeSegment": 2,
        "exchangeInstrumentID": 11120654
    },
    {
        "exchangeSegment": 2,
        "exchangeInstrumentID": 35225
    },
    {
        "exchangeSegment": 2,
        "exchangeInstrumentID": 69082
    },
    {
        "exchangeSegment": 2,
        "exchangeInstrumentID": 9086682
    },
    {
        "exchangeSegment": 2,
        "exchangeInstrumentID": 73387
    },
    {
        "exchangeSegment": 2,
        "exchangeInstrumentID": 10295211
    },
    {
        "exchangeSegment": 2,
        "exchangeInstrumentID": 41316
    },
    {
        "exchangeSegment": 2,
        "exchangeInstrumentID": 10620256
    },
    {
        "exchangeSegment": 2,
        "exchangeInstrumentID": 73698
    },
    {
        "exchangeSegment": 2,
        "exchangeInstrumentID": 11199970
    },
    {
        "exchangeSegment": 2,
        "exchangeInstrumentID": 73531
    },
    {
        "exchangeSegment": 2,
        "exchangeInstrumentID": 11165755
    },
    {
        "exchangeSegment": 2,
        "exchangeInstrumentID": 38966
    },
    {
        "exchangeSegment": 2,
        "exchangeInstrumentID": 10015774
    },
    {
        "exchangeSegment": 2,
        "exchangeInstrumentID": 35985
    },
    {
        "exchangeSegment": 2,
        "exchangeInstrumentID": 73308
    },
    {
        "exchangeSegment": 2,
        "exchangeInstrumentID": 9285468
    },
    {
        "exchangeSegment": 2,
        "exchangeInstrumentID": 39193
    },
    {
        "exchangeSegment": 2,
        "exchangeInstrumentID": 10076564
    },
    {
        "exchangeSegment": 2,
        "exchangeInstrumentID": 73429
    },
    {
        "exchangeSegment": 2,
        "exchangeInstrumentID": 10414037
    },
    {
        "exchangeSegment": 2,
        "exchangeInstrumentID": 43175
    },
    {
        "exchangeSegment": 2,
        "exchangeInstrumentID": 73493
    },
    {
        "exchangeSegment": 2,
        "exchangeInstrumentID": 11126293
    },
    {
        "exchangeSegment": 2,
        "exchangeInstrumentID": 35060
    },
    {
        "exchangeSegment": 2,
        "exchangeInstrumentID": 54834
    },
    {
        "exchangeSegment": 2,
        "exchangeInstrumentID": 9030194
    },
    {
        "exchangeSegment": 2,
        "exchangeInstrumentID": 38452
    },
    {
        "exchangeSegment": 2,
        "exchangeInstrumentID": 35802
    },
    {
        "exchangeSegment": 2,
        "exchangeInstrumentID": 9879514
    },
    {
        "exchangeSegment": 2,
        "exchangeInstrumentID": 39218
    },
    {
        "exchangeSegment": 2,
        "exchangeInstrumentID": 10083007
    },
    {
        "exchangeSegment": 2,
        "exchangeInstrumentID": 69079
    },
    {
        "exchangeSegment": 2,
        "exchangeInstrumentID": 9084119
    },
    {
        "exchangeSegment": 2,
        "exchangeInstrumentID": 39020
    },
    {
        "exchangeSegment": 2,
        "exchangeInstrumentID": 40485
    },
    {
        "exchangeSegment": 2,
        "exchangeInstrumentID": 10029605
    },
    {
        "exchangeSegment": 2,
        "exchangeInstrumentID": 73506
    },
    {
        "exchangeSegment": 2,
        "exchangeInstrumentID": 11139618
    },
    {
        "exchangeSegment": 2,
        "exchangeInstrumentID": 73286
    },
    {
        "exchangeSegment": 2,
        "exchangeInstrumentID": 9237574
    },
    {
        "exchangeSegment": 2,
        "exchangeInstrumentID": 38583
    },
    {
        "exchangeSegment": 2,
        "exchangeInstrumentID": 39344
    },
    {
        "exchangeSegment": 2,
        "exchangeInstrumentID": 9916592
    },
    {
        "exchangeSegment": 2,
        "exchangeInstrumentID": 38675
    },
    {
        "exchangeSegment": 2,
        "exchangeInstrumentID": 39346
    },
    {
        "exchangeSegment": 2,
        "exchangeInstrumentID": 9940146
    },
    {
        "exchangeSegment": 2,
        "exchangeInstrumentID": 73678
    },
    {
        "exchangeSegment": 2,
        "exchangeInstrumentID": 11190990
    },
    {
        "exchangeSegment": 2,
        "exchangeInstrumentID": 40884
    },
    {
        "exchangeSegment": 2,
        "exchangeInstrumentID": 43311
    },
    {
        "exchangeSegment": 2,
        "exchangeInstrumentID": 10509615
    },
    {
        "exchangeSegment": 2,
        "exchangeInstrumentID": 73371
    },
    {
        "exchangeSegment": 2,
        "exchangeInstrumentID": 10289051
    },
    {
        "exchangeSegment": 2,
        "exchangeInstrumentID": 39216
    },
    {
        "exchangeSegment": 2,
        "exchangeInstrumentID": 10082491
    },
    {
        "exchangeSegment": 2,
        "exchangeInstrumentID": 73309
    },
    {
        "exchangeSegment": 2,
        "exchangeInstrumentID": 9347421
    },
    {
        "exchangeSegment": 2,
        "exchangeInstrumentID": 73569
    },
    {
        "exchangeSegment": 2,
        "exchangeInstrumentID": 18907234
    },
    {
        "exchangeSegment": 2,
        "exchangeInstrumentID": 41305
    },
    {
        "exchangeSegment": 2,
        "exchangeInstrumentID": 43356
    },
    {
        "exchangeSegment": 2,
        "exchangeInstrumentID": 10617436
    },
    {
        "exchangeSegment": 2,
        "exchangeInstrumentID": 41524
    },
    {
        "exchangeSegment": 2,
        "exchangeInstrumentID": 10673561
    },
    {
        "exchangeSegment": 2,
        "exchangeInstrumentID": 65553
    },
    {
        "exchangeSegment": 2,
        "exchangeInstrumentID": 9077009
    },
    {
        "exchangeSegment": 2,
        "exchangeInstrumentID": 73288
    },
    {
        "exchangeSegment": 2,
        "exchangeInstrumentID": 9238600
    },
    {
        "exchangeSegment": 2,
        "exchangeInstrumentID": 40392
    },
    {
        "exchangeSegment": 2,
        "exchangeInstrumentID": 73428
    },
    {
        "exchangeSegment": 2,
        "exchangeInstrumentID": 10413780
    },
    {
        "exchangeSegment": 2,
        "exchangeInstrumentID": 35334
    },
    {
        "exchangeSegment": 2,
        "exchangeInstrumentID": 35332
    },
    {
        "exchangeSegment": 2,
        "exchangeInstrumentID": 9080836
    },
    {
        "exchangeSegment": 2,
        "exchangeInstrumentID": 73627
    },
    {
        "exchangeSegment": 2,
        "exchangeInstrumentID": 11181979
    },
    {
        "exchangeSegment": 2,
        "exchangeInstrumentID": 41548
    },
    {
        "exchangeSegment": 2,
        "exchangeInstrumentID": 10679716
    },
    {
        "exchangeSegment": 2,
        "exchangeInstrumentID": 41587
    },
    {
        "exchangeSegment": 2,
        "exchangeInstrumentID": 10689722
    },
    {
        "exchangeSegment": 2,
        "exchangeInstrumentID": 35164
    },
    {
        "exchangeSegment": 2,
        "exchangeInstrumentID": 9037200
    },
    {
        "exchangeSegment": 2,
        "exchangeInstrumentID": 73282
    },
    {
        "exchangeSegment": 2,
        "exchangeInstrumentID": 9179458
    },
    {
        "exchangeSegment": 2,
        "exchangeInstrumentID": 38271
    },
    {
        "exchangeSegment": 2,
        "exchangeInstrumentID": 9833169
    },
    {
        "exchangeSegment": 2,
        "exchangeInstrumentID": 73430
    },
    {
        "exchangeSegment": 2,
        "exchangeInstrumentID": 10415062
    },
    {
        "exchangeSegment": 2,
        "exchangeInstrumentID": 73247
    },
    {
        "exchangeSegment": 2,
        "exchangeInstrumentID": 9135647
    },
    {
        "exchangeSegment": 2,
        "exchangeInstrumentID": 73565
    },
    {
        "exchangeSegment": 2,
        "exchangeInstrumentID": 11172701
    },
    {
        "exchangeSegment": 2,
        "exchangeInstrumentID": 73491
    },
    {
        "exchangeSegment": 2,
        "exchangeInstrumentID": 11125779
    },
    {
        "exchangeSegment": 2,
        "exchangeInstrumentID": 38964
    },
    {
        "exchangeSegment": 2,
        "exchangeInstrumentID": 10015196
    },
    {
        "exchangeSegment": 2,
        "exchangeInstrumentID": 38915
    },
    {
        "exchangeSegment": 2,
        "exchangeInstrumentID": 40385
    },
    {
        "exchangeSegment": 2,
        "exchangeInstrumentID": 10002625
    },
    {
        "exchangeSegment": 2,
        "exchangeInstrumentID": 43418
    },
    {
        "exchangeSegment": 2,
        "exchangeInstrumentID": 73675
    },
    {
        "exchangeSegment": 2,
        "exchangeInstrumentID": 11188683
    },
    {
        "exchangeSegment": 2,
        "exchangeInstrumentID": 73343
    },
    {
        "exchangeSegment": 2,
        "exchangeInstrumentID": 10148735
    },
    {
        "exchangeSegment": 2,
        "exchangeInstrumentID": 39195
    },
    {
        "exchangeSegment": 2,
        "exchangeInstrumentID": 43158
    },
    {
        "exchangeSegment": 2,
        "exchangeInstrumentID": 10077078
    },
    {
        "exchangeSegment": 2,
        "exchangeInstrumentID": 73397
    },
    {
        "exchangeSegment": 2,
        "exchangeInstrumentID": 10411701
    },
    {
        "exchangeSegment": 2,
        "exchangeInstrumentID": 73492
    },
    {
        "exchangeSegment": 2,
        "exchangeInstrumentID": 11126036
    },
    {
        "exchangeSegment": 2,
        "exchangeInstrumentID": 40475
    },
    {
        "exchangeSegment": 2,
        "exchangeInstrumentID": 10404867
    },
    {
        "exchangeSegment": 2,
        "exchangeInstrumentID": 73323
    },
    {
        "exchangeSegment": 2,
        "exchangeInstrumentID": 9391211
    },
    {
        "exchangeSegment": 2,
        "exchangeInstrumentID": 38963
    },
    {
        "exchangeSegment": 2,
        "exchangeInstrumentID": 40410
    },
    {
        "exchangeSegment": 2,
        "exchangeInstrumentID": 10014938
    },
    {
        "exchangeSegment": 2,
        "exchangeInstrumentID": 73396
    },
    {
        "exchangeSegment": 2,
        "exchangeInstrumentID": 10295476
    },
    {
        "exchangeSegment": 2,
        "exchangeInstrumentID": 73489
    },
    {
        "exchangeSegment": 2,
        "exchangeInstrumentID": 11121937
    },
    {
        "exchangeSegment": 2,
        "exchangeInstrumentID": 42278
    },
    {
        "exchangeSegment": 2,
        "exchangeInstrumentID": 73478
    },
    {
        "exchangeSegment": 2,
        "exchangeInstrumentID": 10896646
    },
    {
        "exchangeSegment": 2,
        "exchangeInstrumentID": 73634
    },
    {
        "exchangeSegment": 2,
        "exchangeInstrumentID": 73656
    },
    {
        "exchangeSegment": 2,
        "exchangeInstrumentID": 18923960
    },
    {
        "exchangeSegment": 2,
        "exchangeInstrumentID": 35525
    },
    {
        "exchangeSegment": 2,
        "exchangeInstrumentID": 9148846
    },
    {
        "exchangeSegment": 2,
        "exchangeInstrumentID": 38917
    },
    {
        "exchangeSegment": 2,
        "exchangeInstrumentID": 40388
    },
    {
        "exchangeSegment": 2,
        "exchangeInstrumentID": 10003140
    },
    {
        "exchangeSegment": 2,
        "exchangeInstrumentID": 39123
    },
    {
        "exchangeSegment": 2,
        "exchangeInstrumentID": 41616
    },
    {
        "exchangeSegment": 2,
        "exchangeInstrumentID": 10057104
    },
    {
        "exchangeSegment": 2,
        "exchangeInstrumentID": 73283
    },
    {
        "exchangeSegment": 2,
        "exchangeInstrumentID": 9230147
    },
    {
        "exchangeSegment": 2,
        "exchangeInstrumentID": 73468
    },
    {
        "exchangeSegment": 2,
        "exchangeInstrumentID": 10725628
    },
    {
        "exchangeSegment": 2,
        "exchangeInstrumentID": 73338
    },
    {
        "exchangeSegment": 2,
        "exchangeInstrumentID": 10145402
    },
    {
        "exchangeSegment": 2,
        "exchangeInstrumentID": 73516
    },
    {
        "exchangeSegment": 2,
        "exchangeInstrumentID": 11150124
    },
    {
        "exchangeSegment": 2,
        "exchangeInstrumentID": 38918
    },
    {
        "exchangeSegment": 2,
        "exchangeInstrumentID": 10003400
    },
    {
        "exchangeSegment": 2,
        "exchangeInstrumentID": 57246
    },
    {
        "exchangeSegment": 2,
        "exchangeInstrumentID": 9065118
    },
    {
        "exchangeSegment": 2,
        "exchangeInstrumentID": 41506
    },
    {
        "exchangeSegment": 2,
        "exchangeInstrumentID": 43404
    },
    {
        "exchangeSegment": 2,
        "exchangeInstrumentID": 10668940
    },
    {
        "exchangeSegment": 2,
        "exchangeInstrumentID": 39187
    },
    {
        "exchangeSegment": 2,
        "exchangeInstrumentID": 10074991
    },
    {
        "exchangeSegment": 2,
        "exchangeInstrumentID": 73525
    },
    {
        "exchangeSegment": 2,
        "exchangeInstrumentID": 11160885
    },
    {
        "exchangeSegment": 2,
        "exchangeInstrumentID": 39176
    },
    {
        "exchangeSegment": 2,
        "exchangeInstrumentID": 10071334
    },
    {
        "exchangeSegment": 2,
        "exchangeInstrumentID": 39165
    },
    {
        "exchangeSegment": 2,
        "exchangeInstrumentID": 10067857
    },
    {
        "exchangeSegment": 2,
        "exchangeInstrumentID": 43184
    },
    {
        "exchangeSegment": 2,
        "exchangeInstrumentID": 73495
    },
    {
        "exchangeSegment": 2,
        "exchangeInstrumentID": 11128599
    },
    {
        "exchangeSegment": 2,
        "exchangeInstrumentID": 73278
    },
    {
        "exchangeSegment": 2,
        "exchangeInstrumentID": 9176638
    },
    {
        "exchangeSegment": 2,
        "exchangeInstrumentID": 41554
    },
    {
        "exchangeSegment": 2,
        "exchangeInstrumentID": 10681261
    },
    {
        "exchangeSegment": 2,
        "exchangeInstrumentID": 69089
    },
    {
        "exchangeSegment": 2,
        "exchangeInstrumentID": 9114337
    },
    {
        "exchangeSegment": 2,
        "exchangeInstrumentID": 69092
    },
    {
        "exchangeSegment": 2,
        "exchangeInstrumentID": 9118948
    },
    {
        "exchangeSegment": 2,
        "exchangeInstrumentID": 38291
    },
    {
        "exchangeSegment": 2,
        "exchangeInstrumentID": 35797
    },
    {
        "exchangeSegment": 2,
        "exchangeInstrumentID": 9838293
    },
    {
        "exchangeSegment": 2,
        "exchangeInstrumentID": 73526
    },
    {
        "exchangeSegment": 2,
        "exchangeInstrumentID": 11161142
    },
    {
        "exchangeSegment": 2,
        "exchangeInstrumentID": 38530
    },
    {
        "exchangeSegment": 2,
        "exchangeInstrumentID": 9900990
    },
    {
        "exchangeSegment": 2,
        "exchangeInstrumentID": 38746
    },
    {
        "exchangeSegment": 2,
        "exchangeInstrumentID": 9958342
    },
    {
        "exchangeSegment": 2,
        "exchangeInstrumentID": 69088
    },
    {
        "exchangeSegment": 2,
        "exchangeInstrumentID": 9114080
    },
    {
        "exchangeSegment": 2,
        "exchangeInstrumentID": 73501
    },
    {
        "exchangeSegment": 2,
        "exchangeInstrumentID": 11135517
    },
    {
        "exchangeSegment": 2,
        "exchangeInstrumentID": 40382
    },
    {
        "exchangeSegment": 2,
        "exchangeInstrumentID": 10381044
    },
    {
        "exchangeSegment": 2,
        "exchangeInstrumentID": 73399
    },
    {
        "exchangeSegment": 2,
        "exchangeInstrumentID": 10412215
    },
    {
        "exchangeSegment": 2,
        "exchangeInstrumentID": 38502
    },
    {
        "exchangeSegment": 2,
        "exchangeInstrumentID": 9892497
    },
    {
        "exchangeSegment": 2,
        "exchangeInstrumentID": 73480
    },
    {
        "exchangeSegment": 2,
        "exchangeInstrumentID": 11110408
    },
    {
        "exchangeSegment": 2,
        "exchangeInstrumentID": 35014
    },
    {
        "exchangeSegment": 2,
        "exchangeInstrumentID": 35002
    },
    {
        "exchangeSegment": 2,
        "exchangeInstrumentID": 8998586
    },
    {
        "exchangeSegment": 2,
        "exchangeInstrumentID": 40862
    },
    {
        "exchangeSegment": 2,
        "exchangeInstrumentID": 10503950
    },
    {
        "exchangeSegment": 2,
        "exchangeInstrumentID": 73496
    },
    {
        "exchangeSegment": 2,
        "exchangeInstrumentID": 11129624
    },
    {
        "exchangeSegment": 2,
        "exchangeInstrumentID": 73521
    },
    {
        "exchangeSegment": 2,
        "exchangeInstrumentID": 18894898
    },
    {
        "exchangeSegment": 2,
        "exchangeInstrumentID": 38572
    },
    {
        "exchangeSegment": 2,
        "exchangeInstrumentID": 9913481
    },
    {
        "exchangeSegment": 2,
        "exchangeInstrumentID": 39207
    },
    {
        "exchangeSegment": 2,
        "exchangeInstrumentID": 10080167
    },
    {
        "exchangeSegment": 2,
        "exchangeInstrumentID": 39046
    },
    {
        "exchangeSegment": 2,
        "exchangeInstrumentID": 41574
    },
    {
        "exchangeSegment": 2,
        "exchangeInstrumentID": 10037350
    },
    {
        "exchangeSegment": 2,
        "exchangeInstrumentID": 38727
    },
    {
        "exchangeSegment": 2,
        "exchangeInstrumentID": 9953474
    },
    {
        "exchangeSegment": 2,
        "exchangeInstrumentID": 38468
    },
    {
        "exchangeSegment": 2,
        "exchangeInstrumentID": 35817
    },
    {
        "exchangeSegment": 2,
        "exchangeInstrumentID": 9883625
    },
    {
        "exchangeSegment": 2,
        "exchangeInstrumentID": 73469
    },
    {
        "exchangeSegment": 2,
        "exchangeInstrumentID": 10726909
    },
    {
        "exchangeSegment": 2,
        "exchangeInstrumentID": 41493
    },
    {
        "exchangeSegment": 2,
        "exchangeInstrumentID": 10665605
    },
    {
        "exchangeSegment": 2,
        "exchangeInstrumentID": 39003
    },
    {
        "exchangeSegment": 2,
        "exchangeInstrumentID": 10025250
    },
    {
        "exchangeSegment": 2,
        "exchangeInstrumentID": 35450
    },
    {
        "exchangeSegment": 2,
        "exchangeInstrumentID": 9110557
    },
    {
        "exchangeSegment": 2,
        "exchangeInstrumentID": 35148
    },
    {
        "exchangeSegment": 2,
        "exchangeInstrumentID": 35212
    },
    {
        "exchangeSegment": 2,
        "exchangeInstrumentID": 9033100
    },
    {
        "exchangeSegment": 2,
        "exchangeInstrumentID": 73427
    },
    {
        "exchangeSegment": 2,
        "exchangeInstrumentID": 10412755
    },
    {
        "exchangeSegment": 2,
        "exchangeInstrumentID": 73511
    },
    {
        "exchangeSegment": 2,
        "exchangeInstrumentID": 11145767
    },
    {
        "exchangeSegment": 2,
        "exchangeInstrumentID": 9129404
    },
    {
        "exchangeSegment": 2,
        "exchangeInstrumentID": 73304
    },
    {
        "exchangeSegment": 2,
        "exchangeInstrumentID": 9242456
    },
    {
        "exchangeSegment": 2,
        "exchangeInstrumentID": 39695
    },
    {
        "exchangeSegment": 2,
        "exchangeInstrumentID": 10205132
    },
    {
        "exchangeSegment": 2,
        "exchangeInstrumentID": 73507
    },
    {
        "exchangeSegment": 2,
        "exchangeInstrumentID": 11139875
    },
    {
        "exchangeSegment": 2,
        "exchangeInstrumentID": 54835
    },
    {
        "exchangeSegment": 2,
        "exchangeInstrumentID": 9062195
    },
    {
        "exchangeSegment": 2,
        "exchangeInstrumentID": 41287
    },
    {
        "exchangeSegment": 2,
        "exchangeInstrumentID": 10612811
    },
    {
        "exchangeSegment": 2,
        "exchangeInstrumentID": 73633
    },
    {
        "exchangeSegment": 2,
        "exchangeInstrumentID": 11184289
    },
    {
        "exchangeSegment": 2,
        "exchangeInstrumentID": 40876
    },
    {
        "exchangeSegment": 2,
        "exchangeInstrumentID": 10507554
    },
    {
        "exchangeSegment": 2,
        "exchangeInstrumentID": 73657
    },
    {
        "exchangeSegment": 2,
        "exchangeInstrumentID": 18929593
    },
    {
        "exchangeSegment": 2,
        "exchangeInstrumentID": 41408
    },
    {
        "exchangeSegment": 2,
        "exchangeInstrumentID": 10643835
    },
    {
        "exchangeSegment": 2,
        "exchangeInstrumentID": 73508
    },
    {
        "exchangeSegment": 2,
        "exchangeInstrumentID": 11140132
    },
    {
        "exchangeSegment": 2,
        "exchangeInstrumentID": 35073
    },
    {
        "exchangeSegment": 2,
        "exchangeInstrumentID": 9013748
    },
    {
        "exchangeSegment": 2,
        "exchangeInstrumentID": 40484
    },
    {
        "exchangeSegment": 2,
        "exchangeInstrumentID": 10407173
    },
    {
        "exchangeSegment": 2,
        "exchangeInstrumentID": 73433
    },
    {
        "exchangeSegment": 2,
        "exchangeInstrumentID": 10418393
    },
    {
        "exchangeSegment": 2,
        "exchangeInstrumentID": 73498
    },
    {
        "exchangeSegment": 2,
        "exchangeInstrumentID": 11131674
    },
    {
        "exchangeSegment": 2,
        "exchangeInstrumentID": 41322
    },
    {
        "exchangeSegment": 2,
        "exchangeInstrumentID": 43368
    },
    {
        "exchangeSegment": 2,
        "exchangeInstrumentID": 10621800
    },
    {
        "exchangeSegment": 2,
        "exchangeInstrumentID": 39903
    },
    {
        "exchangeSegment": 2,
        "exchangeInstrumentID": 73370
    },
    {
        "exchangeSegment": 2,
        "exchangeInstrumentID": 10288538
    },
    {
        "exchangeSegment": 2,
        "exchangeInstrumentID": 73263
    },
    {
        "exchangeSegment": 2,
        "exchangeInstrumentID": 9136687
    },
    {
        "exchangeSegment": 2,
        "exchangeInstrumentID": 39180
    },
    {
        "exchangeSegment": 2,
        "exchangeInstrumentID": 10073184
    },
    {
        "exchangeSegment": 2,
        "exchangeInstrumentID": 35295
    },
    {
        "exchangeSegment": 2,
        "exchangeInstrumentID": 9070745
    },
    {
        "exchangeSegment": 2,
        "exchangeInstrumentID": 73285
    },
    {
        "exchangeSegment": 2,
        "exchangeInstrumentID": 9237317
    },
    {
        "exchangeSegment": 2,
        "exchangeInstrumentID": 41300
    },
    {
        "exchangeSegment": 2,
        "exchangeInstrumentID": 10616144
    },
    {
        "exchangeSegment": 2,
        "exchangeInstrumentID": 38806
    },
    {
        "exchangeSegment": 2,
        "exchangeInstrumentID": 9974239
    },
    {
        "exchangeSegment": 2,
        "exchangeInstrumentID": 73669
    },
    {
        "exchangeSegment": 2,
        "exchangeInstrumentID": 11185093
    },
    {
        "exchangeSegment": 2,
        "exchangeInstrumentID": 41528
    },
    {
        "exchangeSegment": 2,
        "exchangeInstrumentID": 10674586
    },
    {
        "exchangeSegment": 2,
        "exchangeInstrumentID": 73502
    },
    {
        "exchangeSegment": 2,
        "exchangeInstrumentID": 73503
    },
    {
        "exchangeSegment": 2,
        "exchangeInstrumentID": 18890015
    },
    {
        "exchangeSegment": 2,
        "exchangeInstrumentID": 39039
    },
    {
        "exchangeSegment": 2,
        "exchangeInstrumentID": 10035013
    },
    {
        "exchangeSegment": 2,
        "exchangeInstrumentID": 69081
    },
    {
        "exchangeSegment": 2,
        "exchangeInstrumentID": 9086169
    },
    {
        "exchangeSegment": 2,
        "exchangeInstrumentID": 73310
    },
    {
        "exchangeSegment": 2,
        "exchangeInstrumentID": 9388638
    },
    {
        "exchangeSegment": 2,
        "exchangeInstrumentID": 73472
    },
    {
        "exchangeSegment": 2,
        "exchangeInstrumentID": 10727168
    },
    {
        "exchangeSegment": 2,
        "exchangeInstrumentID": 41323
    },
    {
        "exchangeSegment": 2,
        "exchangeInstrumentID": 10622057
    },
    {
        "exchangeSegment": 2,
        "exchangeInstrumentID": 54449
    },
    {
        "exchangeSegment": 2,
        "exchangeInstrumentID": 11137201
    },
    {
        "exchangeSegment": 2,
        "exchangeInstrumentID": 73398
    },
    {
        "exchangeSegment": 2,
        "exchangeInstrumentID": 10411958
    },
    {
        "exchangeSegment": 2,
        "exchangeInstrumentID": 73366
    },
    {
        "exchangeSegment": 2,
        "exchangeInstrumentID": 10151574
    },
    {
        "exchangeSegment": 2,
        "exchangeInstrumentID": 73632
    },
    {
        "exchangeSegment": 2,
        "exchangeInstrumentID": 11184032
    },
    {
        "exchangeSegment": 2,
        "exchangeInstrumentID": 9014449
    },
    {
        "exchangeSegment": 2,
        "exchangeInstrumentID": 73329
    },
    {
        "exchangeSegment": 2,
        "exchangeInstrumentID": 9635441
    },
    {
        "exchangeSegment": 2,
        "exchangeInstrumentID": 54454
    },
    {
        "exchangeSegment": 2,
        "exchangeInstrumentID": 9014966
    },
    {
        "exchangeSegment": 2,
        "exchangeInstrumentID": 37501
    },
    {
        "exchangeSegment": 2,
        "exchangeInstrumentID": 9635780
    },
    {
        "exchangeSegment": 2,
        "exchangeInstrumentID": 54456
    },
    {
        "exchangeSegment": 2,
        "exchangeInstrumentID": 9016504
    },
    {
        "exchangeSegment": 2,
        "exchangeInstrumentID": 73534
    },
    {
        "exchangeSegment": 2,
        "exchangeInstrumentID": 11166014
    },
    {
        "exchangeSegment": 2,
        "exchangeInstrumentID": 35434
    },
    {
        "exchangeSegment": 2,
        "exchangeInstrumentID": 9106460
    },
    {
        "exchangeSegment": 2,
        "exchangeInstrumentID": 73340
    },
    {
        "exchangeSegment": 2,
        "exchangeInstrumentID": 10145916
    },
    {
        "exchangeSegment": 2,
        "exchangeInstrumentID": 73504
    },
    {
        "exchangeSegment": 2,
        "exchangeInstrumentID": 18890272
    },
    {
        "exchangeSegment": 2,
        "exchangeInstrumentID": 41442
    },
    {
        "exchangeSegment": 2,
        "exchangeInstrumentID": 10652541
    },
    {
        "exchangeSegment": 2,
        "exchangeInstrumentID": 39213
    },
    {
        "exchangeSegment": 2,
        "exchangeInstrumentID": 10081712
    },
    {
        "exchangeSegment": 2,
        "exchangeInstrumentID": 73573
    },
    {
        "exchangeSegment": 2,
        "exchangeInstrumentID": 11175781
    },
    {
        "exchangeSegment": 2,
        "exchangeInstrumentID": 73485
    },
    {
        "exchangeSegment": 2,
        "exchangeInstrumentID": 11112717
    },
    {
        "exchangeSegment": 2,
        "exchangeInstrumentID": 73536
    },
    {
        "exchangeSegment": 2,
        "exchangeInstrumentID": 11169088
    },
    {
        "exchangeSegment": 2,
        "exchangeInstrumentID": 73461
    },
    {
        "exchangeSegment": 2,
        "exchangeInstrumentID": 10437621
    },
    {
        "exchangeSegment": 2,
        "exchangeInstrumentID": 73437
    },
    {
        "exchangeSegment": 2,
        "exchangeInstrumentID": 10436573
    },
    {
        "exchangeSegment": 2,
        "exchangeInstrumentID": 73311
    },
    {
        "exchangeSegment": 2,
        "exchangeInstrumentID": 9388895
    },
    {
        "exchangeSegment": 2,
        "exchangeInstrumentID": 41559
    },
    {
        "exchangeSegment": 2,
        "exchangeInstrumentID": 10682542
    },
    {
        "exchangeSegment": 2,
        "exchangeInstrumentID": 73466
    },
    {
        "exchangeSegment": 2,
        "exchangeInstrumentID": 10716410
    },
    {
        "exchangeSegment": 2,
        "exchangeInstrumentID": 65555
    },
    {
        "exchangeSegment": 2,
        "exchangeInstrumentID": 9079827
    }
]